compmec/strct/__classes__.py
compmec/strct/__init__.py
compmec/strct/element.py
compmec/strct/fields.py
compmec/strct/geometry.py
compmec/strct/material.py
compmec/strct/profile.py
compmec/strct/section.py
compmec/strct/shower.py
compmec/strct/solver.py
compmec/strct/system.py
compmec/strct/verifytype.py
compmec_strct-1.1.1.dist-info/LICENSE.md
compmec_strct-1.1.1.dist-info/METADATA
compmec_strct-1.1.1.dist-info/WHEEL
compmec_strct-1.1.1.dist-info/RECORD
